{
  "JDBC Request" : {
    "transaction" : "JDBC Request",
    "sampleCount" : 10,
    "errorCount" : 0,
    "errorPct" : 0.0,
    "meanResTime" : 1723.0,
    "medianResTime" : 1833.0,
    "minResTime" : 788.0,
    "maxResTime" : 2265.0,
    "pct1ResTime" : 2256.5,
    "pct2ResTime" : 2265.0,
    "pct3ResTime" : 2265.0,
    "throughput" : 4.378283712784588,
    "receivedKBytesPerSec" : 1649.2917784041158,
    "sentKBytesPerSec" : 0.0
  },
  "Total" : {
    "transaction" : "Total",
    "sampleCount" : 10,
    "errorCount" : 0,
    "errorPct" : 0.0,
    "meanResTime" : 1723.0,
    "medianResTime" : 1833.0,
    "minResTime" : 788.0,
    "maxResTime" : 2265.0,
    "pct1ResTime" : 2256.5,
    "pct2ResTime" : 2265.0,
    "pct3ResTime" : 2265.0,
    "throughput" : 4.378283712784588,
    "receivedKBytesPerSec" : 1649.2917784041158,
    "sentKBytesPerSec" : 0.0
  }
}